smsh/__init__.py
smsh/__main__.py
smsh/clients.py
smsh/command/__init__.py
smsh/command/buffered.py
smsh/command/command.py
smsh/command/editor.py
smsh/command/exit.py
smsh/command/unbuffered.py
smsh/session/__init__.py
smsh/session/ephemeral.py
smsh/session/interactive.py
smsh/session/session.py
smsh/target/__init__.py
smsh/target/container.py
smsh/target/instance.py
smsh/target/target.py
smsh/tests/__init__.py
smsh-0.0.11.dist-info/METADATA
smsh-0.0.11.dist-info/RECORD
smsh-0.0.11.dist-info/WHEEL
smsh-0.0.11.dist-info/entry_points.txt
smsh-0.0.11.dist-info/top_level.txt
