Metadata-Version: 2.1
Name: smsh
Version: 0.0.11
Summary: SSH-like Shell via AWS SSM
Home-page: http://github.com/node40/smsh
Author: Lou Ahola
Author-email: lou@hashchain.ca
License: GNU General Public License v3.0
Platform: UNKNOWN
Classifier: Programming Language :: Python :: 2.7
Classifier: Programming Language :: Python :: 3.3
Classifier: Programming Language :: Python :: 3.4
Classifier: Programming Language :: Python :: 3.5
Classifier: Programming Language :: Python :: 3.6
Requires-Dist: argparse
Requires-Dist: boto3
